{
  "routine_name": "2026-06-01 주간 루틴 - 취준/루틴앱/보고서/운동",
  "version": "1.0",
  "timezone": "Asia/Seoul",
  "week_start": "2026-06-01",
  "week_end": "2026-06-07",
  "sleep": {
    "target_bedtime": "00:00",
    "target_wakeup": "08:00",
    "flex_hours": 2
  },
  "completion_records": {},
  "notes": "이번 주는 오전에 루틴앱/취준을 진행하고, 보고서는 팀원 문서 수령 이후 오후 또는 화~수 버퍼에 처리한다. 완료 체크는 날짜별 completion_records에 저장하는 전제를 둔다.",
  "days": [
    {
      "day": "monday",
      "label": "월요일",
      "date": "2026-06-01",
      "blocks": [
        {
          "id": "mon-stretch-001",
          "title": "아침 교정 스트레칭",
          "category": "health",
          "start": "08:10",
          "end": "08:40",
          "duration_minutes": 30,
          "priority": "medium",
          "color": "#10B981",
          "required": true,
          "notes": "골반 교정 20분 + 어깨/거북목 교정 10분"
        },
        {
          "id": "mon-app-001",
          "title": "루틴앱 작업",
          "category": "app_project",
          "start": "09:00",
          "end": "11:00",
          "duration_minutes": 120,
          "priority": "high",
          "color": "#4F46E5",
          "required": true,
          "notes": "에이전트 결과 확인, requirements/design/tasks 정리"
        },
        {
          "id": "mon-career-001",
          "title": "취준 1",
          "category": "career",
          "start": "11:00",
          "end": "12:00",
          "duration_minutes": 60,
          "priority": "high",
          "color": "#2563EB",
          "required": true,
          "notes": "공고 저장, 기업 리스트업, 지원 우선순위 정리"
        },
        {
          "id": "mon-lunch-001",
          "title": "점심",
          "category": "meal",
          "start": "12:00",
          "end": "13:30",
          "duration_minutes": 90,
          "priority": "medium",
          "color": "#F59E0B",
          "required": true,
          "notes": "식사 및 휴식"
        },
        {
          "id": "mon-report-or-career-001",
          "title": "보고서 작업 / 자료 대기 시 취준 2",
          "category": "conditional",
          "start": "13:30",
          "end": "15:30",
          "duration_minutes": 120,
          "priority": "high",
          "color": "#DC2626",
          "required": true,
          "notes": "팀원 문서 받으면 보고서 수정, 못 받으면 취준 2 진행"
        },
        {
          "id": "mon-english-001",
          "title": "영어 공부",
          "category": "english",
          "start": "15:30",
          "end": "16:30",
          "duration_minutes": 60,
          "priority": "medium",
          "color": "#8B5CF6",
          "required": true,
          "notes": "부담 적은 루틴 유지"
        },
        {
          "id": "mon-report-or-app-001",
          "title": "보고서 작업 / 앱 보충",
          "category": "conditional",
          "start": "16:30",
          "end": "17:30",
          "duration_minutes": 60,
          "priority": "high",
          "color": "#DC2626",
          "required": true,
          "notes": "자료 받았으면 보고서, 아니면 루틴앱 보충"
        },
        {
          "id": "mon-rest-001",
          "title": "휴식/운동 준비",
          "category": "rest",
          "start": "17:30",
          "end": "18:30",
          "duration_minutes": 60,
          "priority": "low",
          "color": "#9CA3AF",
          "required": false,
          "notes": "간식, 이동, 운동 준비"
        },
        {
          "id": "mon-fitness-001",
          "title": "헬스",
          "category": "fitness",
          "start": "18:30",
          "end": "20:30",
          "duration_minutes": 120,
          "priority": "high",
          "color": "#EF4444",
          "required": true,
          "notes": "월화목금 운동 루틴"
        },
        {
          "id": "mon-dinner-001",
          "title": "저녁/샤워",
          "category": "meal",
          "start": "20:30",
          "end": "21:40",
          "duration_minutes": 70,
          "priority": "medium",
          "color": "#F59E0B",
          "required": true,
          "notes": "운동 후 식사 및 회복"
        },
        {
          "id": "mon-clean-001",
          "title": "방 청소 20분",
          "category": "cleaning",
          "start": "21:40",
          "end": "22:00",
          "duration_minutes": 20,
          "priority": "medium",
          "color": "#14B8A6",
          "required": true,
          "notes": "타이머 켜고 딱 20분만"
        },
        {
          "id": "mon-plan-001",
          "title": "보고서 보충 / 내일 계획 정리",
          "category": "planning",
          "start": "22:00",
          "end": "23:00",
          "duration_minutes": 60,
          "priority": "medium",
          "color": "#64748B",
          "required": false,
          "notes": "보고서 진행 상황 확인, 화요일 할 일 정리"
        }
      ]
    },
    {
      "day": "tuesday",
      "label": "화요일",
      "date": "2026-06-02",
      "blocks": [
        {
          "id": "tue-stretch-001",
          "title": "아침 교정 스트레칭",
          "category": "health",
          "start": "08:10",
          "end": "08:40",
          "duration_minutes": 30,
          "priority": "medium",
          "color": "#10B981",
          "required": true,
          "notes": "골반 교정 20분 + 어깨/거북목 교정 10분"
        },
        {
          "id": "tue-report-001",
          "title": "보고서 수정 집중",
          "category": "team_project_report",
          "start": "09:00",
          "end": "11:30",
          "duration_minutes": 150,
          "priority": "high",
          "color": "#DC2626",
          "required": true,
          "notes": "화요일 오전 1차 완성 목표"
        },
        {
          "id": "tue-lunch-001",
          "title": "점심",
          "category": "meal",
          "start": "11:30",
          "end": "13:00",
          "duration_minutes": 90,
          "priority": "medium",
          "color": "#F59E0B",
          "required": true,
          "notes": "식사 및 휴식"
        },
        {
          "id": "tue-report-career-001",
          "title": "보고서 최종 정리 / 완료 시 취준",
          "category": "conditional",
          "start": "13:00",
          "end": "15:00",
          "duration_minutes": 120,
          "priority": "high",
          "color": "#DC2626",
          "required": true,
          "notes": "보고서 미완료 시 마무리, 완료했다면 취준으로 전환"
        },
        {
          "id": "tue-english-001",
          "title": "영어 공부",
          "category": "english",
          "start": "15:00",
          "end": "16:00",
          "duration_minutes": 60,
          "priority": "medium",
          "color": "#8B5CF6",
          "required": true,
          "notes": "영어 루틴 유지"
        },
        {
          "id": "tue-app-001",
          "title": "루틴앱 작업",
          "category": "app_project",
          "start": "16:00",
          "end": "17:30",
          "duration_minutes": 90,
          "priority": "high",
          "color": "#4F46E5",
          "required": true,
          "notes": "에이전트 작업물 리뷰, 다음 구현 범위 정리"
        },
        {
          "id": "tue-rest-001",
          "title": "휴식/운동 준비",
          "category": "rest",
          "start": "17:30",
          "end": "18:30",
          "duration_minutes": 60,
          "priority": "low",
          "color": "#9CA3AF",
          "required": false,
          "notes": "간식, 이동, 운동 준비"
        },
        {
          "id": "tue-fitness-001",
          "title": "헬스",
          "category": "fitness",
          "start": "18:30",
          "end": "20:30",
          "duration_minutes": 120,
          "priority": "high",
          "color": "#EF4444",
          "required": true,
          "notes": "월화목금 운동 루틴"
        },
        {
          "id": "tue-dinner-001",
          "title": "저녁/샤워",
          "category": "meal",
          "start": "20:30",
          "end": "21:40",
          "duration_minutes": 70,
          "priority": "medium",
          "color": "#F59E0B",
          "required": true,
          "notes": "운동 후 식사 및 회복"
        },
        {
          "id": "tue-clean-001",
          "title": "방 청소 20분",
          "category": "cleaning",
          "start": "21:40",
          "end": "22:00",
          "duration_minutes": 20,
          "priority": "medium",
          "color": "#14B8A6",
          "required": true,
          "notes": "타이머 켜고 딱 20분만"
        },
        {
          "id": "tue-buffer-001",
          "title": "보고서 미완료 보충 / 완료 시 휴식",
          "category": "buffer",
          "start": "22:00",
          "end": "23:00",
          "duration_minutes": 60,
          "priority": "medium",
          "color": "#64748B",
          "required": false,
          "notes": "보고서가 끝났으면 휴식 또는 가벼운 정리"
        }
      ]
    },
    {
      "day": "wednesday",
      "label": "수요일",
      "date": "2026-06-03",
      "blocks": [
        {
          "id": "wed-stretch-001",
          "title": "아침 교정 스트레칭",
          "category": "health",
          "start": "08:10",
          "end": "08:40",
          "duration_minutes": 30,
          "priority": "medium",
          "color": "#10B981",
          "required": true,
          "notes": "골반 교정 20분 + 어깨/거북목 교정 10분"
        },
        {
          "id": "wed-report-buffer-001",
          "title": "보고서 최종 버퍼 / 제출본 정리",
          "category": "team_project_report",
          "start": "09:00",
          "end": "11:00",
          "duration_minutes": 120,
          "priority": "high",
          "color": "#DC2626",
          "required": true,
          "notes": "보고서가 이미 끝났다면 취준으로 전환"
        },
        {
          "id": "wed-english-001",
          "title": "영어 공부",
          "category": "english",
          "start": "11:00",
          "end": "12:00",
          "duration_minutes": 60,
          "priority": "medium",
          "color": "#8B5CF6",
          "required": true,
          "notes": "영어 루틴 유지"
        },
        {
          "id": "wed-lunch-001",
          "title": "점심",
          "category": "meal",
          "start": "12:00",
          "end": "13:30",
          "duration_minutes": 90,
          "priority": "medium",
          "color": "#F59E0B",
          "required": true,
          "notes": "식사 및 휴식"
        },
        {
          "id": "wed-career-001",
          "title": "취준 1",
          "category": "career",
          "start": "13:30",
          "end": "15:30",
          "duration_minutes": 120,
          "priority": "high",
          "color": "#2563EB",
          "required": true,
          "notes": "이력서/포트폴리오 정리"
        },
        {
          "id": "wed-app-001",
          "title": "루틴앱 개발/에이전트 작업물 검토",
          "category": "app_project",
          "start": "15:30",
          "end": "17:30",
          "duration_minutes": 120,
          "priority": "high",
          "color": "#4F46E5",
          "required": true,
          "notes": "보고서 이후 앱 작업으로 전환"
        },
        {
          "id": "wed-rest-001",
          "title": "휴식/산책/가벼운 정리",
          "category": "rest",
          "start": "17:30",
          "end": "19:00",
          "duration_minutes": 90,
          "priority": "low",
          "color": "#9CA3AF",
          "required": false,
          "notes": "수요일은 운동 없는 회복일"
        },
        {
          "id": "wed-career-002",
          "title": "취준 2",
          "category": "career",
          "start": "19:00",
          "end": "20:30",
          "duration_minutes": 90,
          "priority": "medium",
          "color": "#2563EB",
          "required": false,
          "notes": "기업분석/공고분석"
        },
        {
          "id": "wed-dinner-001",
          "title": "저녁",
          "category": "meal",
          "start": "20:30",
          "end": "21:40",
          "duration_minutes": 70,
          "priority": "medium",
          "color": "#F59E0B",
          "required": true,
          "notes": "식사 및 휴식"
        },
        {
          "id": "wed-clean-001",
          "title": "방 청소 20분",
          "category": "cleaning",
          "start": "21:40",
          "end": "22:00",
          "duration_minutes": 20,
          "priority": "medium",
          "color": "#14B8A6",
          "required": true,
          "notes": "타이머 켜고 딱 20분만"
        },
        {
          "id": "wed-plan-001",
          "title": "루틴앱 내일 할 일 정리",
          "category": "planning",
          "start": "22:00",
          "end": "23:00",
          "duration_minutes": 60,
          "priority": "medium",
          "color": "#64748B",
          "required": false,
          "notes": "목요일 작업 범위 정리"
        }
      ]
    },
    {
      "day": "thursday",
      "label": "목요일",
      "date": "2026-06-04",
      "blocks": [
        {
          "id": "thu-stretch-001",
          "title": "아침 교정 스트레칭",
          "category": "health",
          "start": "08:10",
          "end": "08:40",
          "duration_minutes": 30,
          "priority": "medium",
          "color": "#10B981",
          "required": true,
          "notes": "골반 교정 20분 + 어깨/거북목 교정 10분"
        },
        {
          "id": "thu-career-001",
          "title": "취준 1",
          "category": "career",
          "start": "09:00",
          "end": "11:00",
          "duration_minutes": 120,
          "priority": "high",
          "color": "#2563EB",
          "required": true,
          "notes": "자소서/이력서"
        },
        {
          "id": "thu-english-001",
          "title": "영어 공부",
          "category": "english",
          "start": "11:00",
          "end": "12:00",
          "duration_minutes": 60,
          "priority": "medium",
          "color": "#8B5CF6",
          "required": true,
          "notes": "영어 루틴 유지"
        },
        {
          "id": "thu-lunch-001",
          "title": "점심",
          "category": "meal",
          "start": "12:00",
          "end": "13:30",
          "duration_minutes": 90,
          "priority": "medium",
          "color": "#F59E0B",
          "required": true,
          "notes": "식사 및 휴식"
        },
        {
          "id": "thu-app-001",
          "title": "루틴앱 개발 1",
          "category": "app_project",
          "start": "13:30",
          "end": "15:30",
          "duration_minutes": 120,
          "priority": "high",
          "color": "#4F46E5",
          "required": true,
          "notes": "JSON import/export, localStorage"
        },
        {
          "id": "thu-app-002",
          "title": "루틴앱 개발 2",
          "category": "app_project",
          "start": "15:30",
          "end": "17:30",
          "duration_minutes": 120,
          "priority": "high",
          "color": "#4F46E5",
          "required": true,
          "notes": "주간표 UI, 루틴 블록 표시"
        },
        {
          "id": "thu-rest-001",
          "title": "휴식/운동 준비",
          "category": "rest",
          "start": "17:30",
          "end": "18:30",
          "duration_minutes": 60,
          "priority": "low",
          "color": "#9CA3AF",
          "required": false,
          "notes": "간식, 이동, 운동 준비"
        },
        {
          "id": "thu-fitness-001",
          "title": "헬스",
          "category": "fitness",
          "start": "18:30",
          "end": "20:30",
          "duration_minutes": 120,
          "priority": "high",
          "color": "#EF4444",
          "required": true,
          "notes": "월화목금 운동 루틴"
        },
        {
          "id": "thu-dinner-001",
          "title": "저녁/샤워",
          "category": "meal",
          "start": "20:30",
          "end": "21:40",
          "duration_minutes": 70,
          "priority": "medium",
          "color": "#F59E0B",
          "required": true,
          "notes": "운동 후 식사 및 회복"
        },
        {
          "id": "thu-clean-001",
          "title": "방 청소 20분",
          "category": "cleaning",
          "start": "21:40",
          "end": "22:00",
          "duration_minutes": 20,
          "priority": "medium",
          "color": "#14B8A6",
          "required": true,
          "notes": "타이머 켜고 딱 20분만"
        },
        {
          "id": "thu-plan-001",
          "title": "앱 이슈 정리/내일 작업 계획",
          "category": "planning",
          "start": "22:00",
          "end": "23:00",
          "duration_minutes": 60,
          "priority": "medium",
          "color": "#64748B",
          "required": false,
          "notes": "금요일 작업 우선순위 정리"
        }
      ]
    },
    {
      "day": "friday",
      "label": "금요일",
      "date": "2026-06-05",
      "blocks": [
        {
          "id": "fri-stretch-001",
          "title": "아침 교정 스트레칭",
          "category": "health",
          "start": "08:10",
          "end": "08:40",
          "duration_minutes": 30,
          "priority": "medium",
          "color": "#10B981",
          "required": true,
          "notes": "골반 교정 20분 + 어깨/거북목 교정 10분"
        },
        {
          "id": "fri-career-001",
          "title": "취준 1",
          "category": "career",
          "start": "09:00",
          "end": "11:00",
          "duration_minutes": 120,
          "priority": "high",
          "color": "#2563EB",
          "required": true,
          "notes": "기업분석/지원공고 분석"
        },
        {
          "id": "fri-english-001",
          "title": "영어 공부",
          "category": "english",
          "start": "11:00",
          "end": "12:00",
          "duration_minutes": 60,
          "priority": "medium",
          "color": "#8B5CF6",
          "required": true,
          "notes": "영어 루틴 유지"
        },
        {
          "id": "fri-lunch-001",
          "title": "점심",
          "category": "meal",
          "start": "12:00",
          "end": "13:30",
          "duration_minutes": 90,
          "priority": "medium",
          "color": "#F59E0B",
          "required": true,
          "notes": "식사 및 휴식"
        },
        {
          "id": "fri-app-001",
          "title": "루틴앱 개발 1",
          "category": "app_project",
          "start": "13:30",
          "end": "15:30",
          "duration_minutes": 120,
          "priority": "high",
          "color": "#4F46E5",
          "required": true,
          "notes": "블록 추가/수정/삭제"
        },
        {
          "id": "fri-app-002",
          "title": "루틴앱 개발 2",
          "category": "app_project",
          "start": "15:30",
          "end": "17:00",
          "duration_minutes": 90,
          "priority": "high",
          "color": "#4F46E5",
          "required": true,
          "notes": "날짜별 완료 체크"
        },
        {
          "id": "fri-rest-001",
          "title": "휴식/운동 준비",
          "category": "rest",
          "start": "17:00",
          "end": "18:30",
          "duration_minutes": 90,
          "priority": "low",
          "color": "#9CA3AF",
          "required": false,
          "notes": "간식, 이동, 운동 준비"
        },
        {
          "id": "fri-fitness-001",
          "title": "헬스",
          "category": "fitness",
          "start": "18:30",
          "end": "20:30",
          "duration_minutes": 120,
          "priority": "high",
          "color": "#EF4444",
          "required": true,
          "notes": "월화목금 운동 루틴"
        },
        {
          "id": "fri-dinner-001",
          "title": "저녁/샤워",
          "category": "meal",
          "start": "20:30",
          "end": "21:40",
          "duration_minutes": 70,
          "priority": "medium",
          "color": "#F59E0B",
          "required": true,
          "notes": "운동 후 식사 및 회복"
        },
        {
          "id": "fri-clean-001",
          "title": "방 청소 20분",
          "category": "cleaning",
          "start": "21:40",
          "end": "22:00",
          "duration_minutes": 20,
          "priority": "medium",
          "color": "#14B8A6",
          "required": true,
          "notes": "타이머 켜고 딱 20분만"
        },
        {
          "id": "fri-review-001",
          "title": "이번 주 앱 진행상황 정리",
          "category": "planning",
          "start": "22:00",
          "end": "23:00",
          "duration_minutes": 60,
          "priority": "medium",
          "color": "#64748B",
          "required": false,
          "notes": "앱이 대충이라도 돌아가는 상태인지 확인"
        }
      ]
    },
    {
      "day": "saturday",
      "label": "토요일",
      "date": "2026-06-06",
      "blocks": [
        {
          "id": "sat-stretch-001",
          "title": "아침 교정 스트레칭",
          "category": "health",
          "start": "08:30",
          "end": "09:00",
          "duration_minutes": 30,
          "priority": "medium",
          "color": "#10B981",
          "required": true,
          "notes": "골반 교정 20분 + 어깨/거북목 교정 10분"
        },
        {
          "id": "sat-morning-001",
          "title": "가벼운 정리/아침 준비",
          "category": "rest",
          "start": "09:00",
          "end": "10:00",
          "duration_minutes": 60,
          "priority": "low",
          "color": "#9CA3AF",
          "required": false,
          "notes": "주말 시작 정리"
        },
        {
          "id": "sat-app-001",
          "title": "루틴앱 보충/버그 수정",
          "category": "app_project",
          "start": "10:00",
          "end": "12:00",
          "duration_minutes": 120,
          "priority": "high",
          "color": "#4F46E5",
          "required": true,
          "notes": "평일에 밀린 앱 작업 보충"
        },
        {
          "id": "sat-lunch-001",
          "title": "점심",
          "category": "meal",
          "start": "12:00",
          "end": "13:30",
          "duration_minutes": 90,
          "priority": "medium",
          "color": "#F59E0B",
          "required": true,
          "notes": "식사 및 휴식"
        },
        {
          "id": "sat-drawing-001",
          "title": "그림",
          "category": "drawing",
          "start": "13:30",
          "end": "19:30",
          "duration_minutes": 360,
          "priority": "medium",
          "color": "#EC4899",
          "required": true,
          "notes": "주 2회 6시간 그림 몰입 블록"
        },
        {
          "id": "sat-dinner-001",
          "title": "저녁",
          "category": "meal",
          "start": "19:30",
          "end": "21:00",
          "duration_minutes": 90,
          "priority": "medium",
          "color": "#F59E0B",
          "required": true,
          "notes": "식사 및 휴식"
        },
        {
          "id": "sat-clean-001",
          "title": "방 청소 20분",
          "category": "cleaning",
          "start": "21:00",
          "end": "21:20",
          "duration_minutes": 20,
          "priority": "medium",
          "color": "#14B8A6",
          "required": true,
          "notes": "타이머 켜고 딱 20분만"
        },
        {
          "id": "sat-free-001",
          "title": "자유시간/휴식",
          "category": "rest",
          "start": "21:20",
          "end": "22:30",
          "duration_minutes": 70,
          "priority": "low",
          "color": "#9CA3AF",
          "required": false,
          "notes": "주말 휴식"
        },
        {
          "id": "sat-plan-001",
          "title": "내일 계획 정리",
          "category": "planning",
          "start": "22:30",
          "end": "23:00",
          "duration_minutes": 30,
          "priority": "low",
          "color": "#64748B",
          "required": false,
          "notes": "일요일 할 일 3개만 정리"
        }
      ]
    },
    {
      "day": "sunday",
      "label": "일요일",
      "date": "2026-06-07",
      "blocks": [
        {
          "id": "sun-stretch-001",
          "title": "아침 교정 스트레칭",
          "category": "health",
          "start": "08:30",
          "end": "09:00",
          "duration_minutes": 30,
          "priority": "medium",
          "color": "#10B981",
          "required": true,
          "notes": "골반 교정 20분 + 어깨/거북목 교정 10분"
        },
        {
          "id": "sun-review-001",
          "title": "이번 주 루틴 회고",
          "category": "planning",
          "start": "09:00",
          "end": "10:00",
          "duration_minutes": 60,
          "priority": "medium",
          "color": "#64748B",
          "required": true,
          "notes": "성공/실패 요인 확인, 다음 주 조정"
        },
        {
          "id": "sun-app-001",
          "title": "루틴앱 마무리/다음 기능 정리",
          "category": "app_project",
          "start": "10:00",
          "end": "12:00",
          "duration_minutes": 120,
          "priority": "high",
          "color": "#4F46E5",
          "required": true,
          "notes": "MVP 상태 점검, 다음 기능 목록 정리"
        },
        {
          "id": "sun-lunch-001",
          "title": "점심",
          "category": "meal",
          "start": "12:00",
          "end": "13:30",
          "duration_minutes": 90,
          "priority": "medium",
          "color": "#F59E0B",
          "required": true,
          "notes": "식사 및 휴식"
        },
        {
          "id": "sun-drawing-001",
          "title": "그림",
          "category": "drawing",
          "start": "13:30",
          "end": "19:30",
          "duration_minutes": 360,
          "priority": "medium",
          "color": "#EC4899",
          "required": true,
          "notes": "주 2회 6시간 그림 몰입 블록"
        },
        {
          "id": "sun-dinner-001",
          "title": "저녁",
          "category": "meal",
          "start": "19:30",
          "end": "21:00",
          "duration_minutes": 90,
          "priority": "medium",
          "color": "#F59E0B",
          "required": true,
          "notes": "식사 및 휴식"
        },
        {
          "id": "sun-clean-001",
          "title": "방 청소 20분",
          "category": "cleaning",
          "start": "21:00",
          "end": "21:20",
          "duration_minutes": 20,
          "priority": "medium",
          "color": "#14B8A6",
          "required": true,
          "notes": "타이머 켜고 딱 20분만"
        },
        {
          "id": "sun-nextweek-001",
          "title": "다음 주 스케줄 작성",
          "category": "planning",
          "start": "21:20",
          "end": "22:00",
          "duration_minutes": 40,
          "priority": "high",
          "color": "#64748B",
          "required": true,
          "notes": "다음 주 목표 반영해서 루틴 업데이트"
        },
        {
          "id": "sun-rest-001",
          "title": "휴식/취침 준비",
          "category": "rest",
          "start": "22:00",
          "end": "23:00",
          "duration_minutes": 60,
          "priority": "low",
          "color": "#9CA3AF",
          "required": false,
          "notes": "월요일 시작을 위한 마무리"
        }
      ]
    }
  ]
}